graphteasar/.DS_Store
graphteasar/__init__.py
graphteasar/find_root.py
graphteasar/skeletonize_mesh.py
graphteasar/utils.py
graphteasar-0.1.1.dist-info/LICENSE
graphteasar-0.1.1.dist-info/METADATA
graphteasar-0.1.1.dist-info/WHEEL
graphteasar-0.1.1.dist-info/RECORD
